storybro/__init__.py
storybro/cli/__init__.py
storybro/cli/commands/models/__init__.py
storybro/cli/commands/models/get.py
storybro/cli/commands/models/list.py
storybro/cli/commands/play.py
storybro/cli/commands/stories/__init__.py
storybro/cli/commands/stories/list.py
storybro/cli/config.py
storybro/data/__init__.py
storybro/data/censored_words.txt
storybro/data/grammars/__init__.py
storybro/data/grammars/apocalyptic.json
storybro/data/grammars/fantasy.json
storybro/data/splash.txt
storybro/data/story_data.yaml
storybro/generation/__init__.py
storybro/generation/gpt2/LICENSE
storybro/generation/gpt2/__init__.py
storybro/generation/gpt2/encoder.py
storybro/generation/gpt2/generator.py
storybro/generation/gpt2/model.py
storybro/generation/gpt2/sample.py
storybro/models/__init__.py
storybro/models/manager.py
storybro/models/model.py
storybro/models/registry.py
storybro/play/__init__.py
storybro/play/block_formatter.py
storybro/play/player.py
storybro/play/settings.py
storybro/stories/__init__.py
storybro/stories/block.py
storybro/stories/manager.py
storybro/stories/story.py
storybro/story/__init__.py
storybro/story/grammars.py
storybro/story/story_manager.py
storybro/story/utils.py
storybro/utils.py
storybro-0.1.0.dist-info/entry_points.txt
storybro-0.1.0.dist-info/LICENSE
storybro-0.1.0.dist-info/WHEEL
storybro-0.1.0.dist-info/METADATA
storybro-0.1.0.dist-info/RECORD
