Metadata-Version: 2.1
Name: storybro
Version: 0.1.0
Summary: A GPT-2 based AI assisted storytelling tool
Home-page: https://github.com/storybro/storybro
License: MIT
Keywords: gpt2,gpt-2
Author: Nick Walton
Author-email: unknown@example.com
Requires-Python: >=3.6.8,<3.7.0
Classifier: License :: OSI Approved :: MIT License
Classifier: Programming Language :: Python :: 3
Requires-Dist: appdirs (==1.4.3)
Requires-Dist: click (==7.0)
Requires-Dist: click-config-file (==0.5.0)
Requires-Dist: cmd2 (==0.9.22)
Requires-Dist: cryptography (>=2.8,<2.9)
Requires-Dist: func_timeout (==4.3.5)
Requires-Dist: google-cloud-storage (==1.23.0)
Requires-Dist: gsutil (==4.46)
Requires-Dist: importlib_resources (>=1.0.2,<1.1.0)
Requires-Dist: numpy (==1.18.0)
Requires-Dist: playsound (==1.2.2)
Requires-Dist: profanityfilter (==2.0.6)
Requires-Dist: prompt_toolkit (==3.0.2)
Requires-Dist: pyyaml (==5.2)
Requires-Dist: regex (==2019.12.20)
Requires-Dist: tensorflow (==1.15)
Requires-Dist: tracery (==0.1.1)
Project-URL: Repository, https://github.com/storybro/storybro
